CHANGES.txt
DEPENDENCES.txt
README.txt
setup.py
src/ng/__init__.py
src/ng.skin.zopelada.egg-info/PKG-INFO
src/ng.skin.zopelada.egg-info/SOURCES.txt
src/ng.skin.zopelada.egg-info/dependency_links.txt
src/ng.skin.zopelada.egg-info/namespace_packages.txt
src/ng.skin.zopelada.egg-info/not-zip-safe
src/ng.skin.zopelada.egg-info/requires.txt
src/ng.skin.zopelada.egg-info/top_level.txt
src/ng/skin/__init__.py
src/ng/skin/zopelada/__init__.py
src/ng/skin/zopelada/configure.zcml
src/ng/skin/zopelada/interfaces.py
src/ng/skin/zopelada/ng.skin.zopelada.txt
src/ng/skin/zopelada/remark.txt
src/ng/skin/zopelada/skeleton.pt
src/ng/skin/zopelada/style.css
src/ng/skin/zopelada/style_ie.css
src/ng/skin/zopelada/etc/ng.skin.zopelada-configure.zcml
src/ng/skin/zopelada/idea/__init__.py
src/ng/skin/zopelada/idea/configure.zcml
src/ng/skin/zopelada/idea/idea.pt
src/ng/skin/zopelada/idea/idea.py
src/ng/skin/zopelada/images/angledown.gif
src/ng/skin/zopelada/images/angleup.gif
src/ng/skin/zopelada/images/bottomlogo.png
src/ng/skin/zopelada/images/logo.gif
src/ng/skin/zopelada/images/logo.png
src/ng/skin/zopelada/images/toplogo.png
src/ng/skin/zopelada/main/__init__.py
src/ng/skin/zopelada/main/configure.zcml
src/ng/skin/zopelada/main/main.css
src/ng/skin/zopelada/main/main.pt